torch_efd/__init__.py
torch_efd/compute.py
torch_efd/measure.py
torch_efd/reconstruct.py
torch_efd/render.py
torch_efd/transforms.py
torch_efd-1.0.0.dist-info/LICENSE
torch_efd-1.0.0.dist-info/METADATA
torch_efd-1.0.0.dist-info/WHEEL
torch_efd-1.0.0.dist-info/RECORD
