Metadata-Version: 2.1
Name: torch-efd
Version: 1.0.0
Summary: Elliptic Fourier Descriptors in PyTorch
License: MIT
Author: Felix Peppert
Author-email: felix.peppert@pm.me
Requires-Python: >=3.10,<4.0
Classifier: License :: OSI Approved :: MIT License
Classifier: Programming Language :: Python :: 3
Classifier: Programming Language :: Python :: 3.10
Classifier: Programming Language :: Python :: 3.11
Classifier: Programming Language :: Python :: 3.12
Provides-Extra: plot
Provides-Extra: render
Requires-Dist: matplotlib (>=3.0.0,<4.0.0) ; extra == "plot"
Requires-Dist: scikit-image (>=0.24,<0.25) ; extra == "render"
Requires-Dist: scipy (>=1.0.0,<2.0.0) ; extra == "render"
Requires-Dist: torch (>=2.0,<3.0)
